{
    "title1": "รายงานรายชื่อผู้ค้างชำระกู้ยืมเงินทุนประกอบอาชีพติดต่อตั้งแต่ 2-12 งวด ขึ้นไป",
    "title2": "ประจำเดือน {เดือน} 2562",
    "fiscalYear": "2562",
    "reportDataDate": "14 พฤษจิกายน 2562",
    "data": [
        {
            "paymentType": "OFFICE",
            "outstandingDebtBalance": "0.00",
            "documentDate": "2019-07-24T17:00:00.000Z",
            "documentNumber": "นท/2562/0001",
            "startDate": "2019-07-24T17:00:00.000Z",
            "endDate": "2022-07-27T17:00:00.000Z",
            "loanAmount": "80000000.00",
            "installmentAmount": "2222222.22",
            "installmentLastAmount": "0.00",
            "installmentPeriodValue": 1,
            "installmentTimes": 36,
            "borrowerIdCardNo": "1809900613234",
            "guarantorIdCardNo": "1809900611231",
            "borrowerName": "นายสิทธิชัย สันติวรกุล",
            "guarantorName": "นายสิทธิชัย สันติวรกุล",
            "broughtForward": "10000.00",
            "totalPaidJanuary": "0.00",
            "totalPaidFebruary": "0.00",
            "totalPaidMarch": "0.00",
            "totalPaidApril": "0.00",
            "totalPaidMay": "0.00",
            "totalPaidJune": "0.00",
            "totalPaidJuly": "0.00",
            "totalPaidAugust": "0.00",
            "totalPaidSeptember": "0.00",
            "totalPaidOctober": "0.00",
            "totalPaidNovember": "0.00",
            "totalPaidDecember": "0.00",
            "totalPaidAllMonth": "0.00",
            "lastPaidDate": "2008-10-09T17:00:00.000Z",
            "currentDate": "2019-11-13",
            "installmentsTimesDue": "5",
            "currentTempExpectedPaidAmount": "11111111.10",
            "installmentsAmountDue": "11111111.100000000000000000000000000000",
            "tempPaidAmount": "10000.00",
            "paidAmount": "10000.00",
            "installmentsTimesOverDue": 11101111.1,
            "installmentsAmountOverDue": 5
        },
        {
            "paymentType": "OFFICE",
            "outstandingDebtBalance": "30000.00",
            "documentDate": "2019-08-14T17:00:00.000Z",
            "documentNumber": "กท/2562/0010",
            "startDate": "2019-08-14T17:00:00.000Z",
            "endDate": "2023-07-31T17:00:00.000Z",
            "loanAmount": "30000.00",
            "installmentAmount": "1200.00",
            "installmentLastAmount": "0.00",
            "installmentPeriodValue": 1,
            "installmentTimes": 25,
            "borrowerIdCardNo": "3102001946582",
            "guarantorIdCardNo": "3102001946663",
            "borrowerName": "นางยุพา รุ่งเรือง",
            "guarantorName": "นายเปี่ยมศักดิ์ รุ่งเรือง",
            "broughtForward": "1500.00",
            "totalPaidJanuary": "0.00",
            "totalPaidFebruary": "0.00",
            "totalPaidMarch": "0.00",
            "totalPaidApril": "0.00",
            "totalPaidMay": "0.00",
            "totalPaidJune": "0.00",
            "totalPaidJuly": "0.00",
            "totalPaidAugust": "0.00",
            "totalPaidSeptember": "0.00",
            "totalPaidOctober": "0.00",
            "totalPaidNovember": "0.00",
            "totalPaidDecember": "0.00",
            "totalPaidAllMonth": "0.00",
            "lastPaidDate": "2008-06-19T17:00:00.000Z",
            "currentDate": "2019-11-13",
            "installmentsTimesDue": "4",
            "currentTempExpectedPaidAmount": "4800.00",
            "installmentsAmountDue": "4800.000000000000000000000000000000",
            "tempPaidAmount": "1500.00",
            "paidAmount": "1500.00",
            "installmentsTimesOverDue": 3300,
            "installmentsAmountOverDue": 3
        },
        {
            "paymentType": "OFFICE",
            "outstandingDebtBalance": "30000.00",
            "documentDate": "2019-08-14T17:00:00.000Z",
            "documentNumber": "กท/2562/0010",
            "startDate": "2019-08-14T17:00:00.000Z",
            "endDate": "2023-07-31T17:00:00.000Z",
            "loanAmount": "30000.00",
            "installmentAmount": "1200.00",
            "installmentLastAmount": "0.00",
            "installmentPeriodValue": 1,
            "installmentTimes": 25,
            "borrowerIdCardNo": "1309900002674",
            "guarantorIdCardNo": "1809900616724",
            "borrowerName": "น.ส.ภัททิยา อัครทวี",
            "guarantorName": "นายทดสอบ ทดสอบ",
            "broughtForward": "1500.00",
            "totalPaidJanuary": "0.00",
            "totalPaidFebruary": "0.00",
            "totalPaidMarch": "0.00",
            "totalPaidApril": "0.00",
            "totalPaidMay": "0.00",
            "totalPaidJune": "0.00",
            "totalPaidJuly": "0.00",
            "totalPaidAugust": "0.00",
            "totalPaidSeptember": "0.00",
            "totalPaidOctober": "0.00",
            "totalPaidNovember": "0.00",
            "totalPaidDecember": "0.00",
            "totalPaidAllMonth": "0.00",
            "lastPaidDate": "2008-06-19T17:00:00.000Z",
            "currentDate": "2019-11-13",
            "installmentsTimesDue": "4",
            "currentTempExpectedPaidAmount": "4800.00",
            "installmentsAmountDue": "4800.000000000000000000000000000000",
            "tempPaidAmount": "1500.00",
            "paidAmount": "1500.00",
            "installmentsTimesOverDue": 3300,
            "installmentsAmountOverDue": 3
        },
        {
            "paymentType": "OFFICE",
            "outstandingDebtBalance": "1000.00",
            "documentDate": "2019-08-25T17:00:00.000Z",
            "documentNumber": "กท/2562/0016",
            "startDate": "2019-08-25T17:00:00.000Z",
            "endDate": "2020-04-04T17:00:00.000Z",
            "loanAmount": "1000.00",
            "installmentAmount": "133.00",
            "installmentLastAmount": "69.00",
            "installmentPeriodValue": 1,
            "installmentTimes": 8,
            "borrowerIdCardNo": "3959900370861",
            "guarantorIdCardNo": "3959900370879",
            "borrowerName": "นางตวงพร ฐานอิทธิ",
            "guarantorName": "นายมานิต ฐานอิทธิ",
            "broughtForward": "10000.00",
            "totalPaidJanuary": "0.00",
            "totalPaidFebruary": "0.00",
            "totalPaidMarch": "0.00",
            "totalPaidApril": "0.00",
            "totalPaidMay": "0.00",
            "totalPaidJune": "0.00",
            "totalPaidJuly": "0.00",
            "totalPaidAugust": "0.00",
            "totalPaidSeptember": "0.00",
            "totalPaidOctober": "0.00",
            "totalPaidNovember": "0.00",
            "totalPaidDecember": "0.00",
            "totalPaidAllMonth": "0.00",
            "lastPaidDate": "2008-11-24T17:00:00.000Z",
            "currentDate": "2019-11-13",
            "installmentsTimesDue": "4",
            "currentTempExpectedPaidAmount": "532.00",
            "installmentsAmountDue": "532.000000000000000000000000000000",
            "tempPaidAmount": "10000.00",
            "paidAmount": "10000.00",
            "installmentsTimesOverDue": -9468,
            "installmentsAmountOverDue": 0
        },
        {
            "paymentType": "OFFICE",
            "outstandingDebtBalance": "1000.00",
            "documentDate": "2019-08-25T17:00:00.000Z",
            "documentNumber": "กท/2562/0016",
            "startDate": "2019-08-25T17:00:00.000Z",
            "endDate": "2020-04-04T17:00:00.000Z",
            "loanAmount": "1000.00",
            "installmentAmount": "133.00",
            "installmentLastAmount": "69.00",
            "installmentPeriodValue": 1,
            "installmentTimes": 8,
            "borrowerIdCardNo": "1809900612321",
            "guarantorIdCardNo": "1809900612312",
            "borrowerName": "นายสิทธิชัย สันติวรกุล",
            "guarantorName": "นายสิทธิชัย สันติวรกุล",
            "broughtForward": "10000.00",
            "totalPaidJanuary": "0.00",
            "totalPaidFebruary": "0.00",
            "totalPaidMarch": "0.00",
            "totalPaidApril": "0.00",
            "totalPaidMay": "0.00",
            "totalPaidJune": "0.00",
            "totalPaidJuly": "0.00",
            "totalPaidAugust": "0.00",
            "totalPaidSeptember": "0.00",
            "totalPaidOctober": "0.00",
            "totalPaidNovember": "0.00",
            "totalPaidDecember": "0.00",
            "totalPaidAllMonth": "0.00",
            "lastPaidDate": "2008-11-24T17:00:00.000Z",
            "currentDate": "2019-11-13",
            "installmentsTimesDue": "4",
            "currentTempExpectedPaidAmount": "532.00",
            "installmentsAmountDue": "532.000000000000000000000000000000",
            "tempPaidAmount": "10000.00",
            "paidAmount": "10000.00",
            "installmentsTimesOverDue": -9468,
            "installmentsAmountOverDue": 0
        },
        {
            "paymentType": "OFFICE",
            "outstandingDebtBalance": "34560.00",
            "documentDate": "2019-08-26T17:00:00.000Z",
            "documentNumber": "กท/2562/0017",
            "startDate": "2019-08-26T17:00:00.000Z",
            "endDate": "2022-01-06T17:00:00.000Z",
            "loanAmount": "34560.00",
            "installmentAmount": "1231.00",
            "installmentLastAmount": "92.00",
            "installmentPeriodValue": 1,
            "installmentTimes": 29,
            "borrowerIdCardNo": "3959900370461",
            "guarantorIdCardNo": "3200101202795",
            "borrowerName": "นางพรรณี ชัยศรี",
            "guarantorName": "นางเรณู ประเสริฐวิทย์",
            "broughtForward": "6000.00",
            "totalPaidJanuary": "0.00",
            "totalPaidFebruary": "0.00",
            "totalPaidMarch": "0.00",
            "totalPaidApril": "0.00",
            "totalPaidMay": "0.00",
            "totalPaidJune": "0.00",
            "totalPaidJuly": "0.00",
            "totalPaidAugust": "0.00",
            "totalPaidSeptember": "0.00",
            "totalPaidOctober": "0.00",
            "totalPaidNovember": "0.00",
            "totalPaidDecember": "0.00",
            "totalPaidAllMonth": "0.00",
            "lastPaidDate": "2019-11-30T17:00:00.000Z",
            "currentDate": "2019-11-13",
            "installmentsTimesDue": "4",
            "currentTempExpectedPaidAmount": "4924.00",
            "installmentsAmountDue": "4924.000000000000000000000000000000",
            "tempPaidAmount": "6000.00",
            "paidAmount": "6000.00",
            "installmentsTimesOverDue": -1076,
            "installmentsAmountOverDue": 0
        },
        {
            "paymentType": "CS",
            "outstandingDebtBalance": "34560.00",
            "documentDate": "2019-08-26T17:00:00.000Z",
            "documentNumber": "กท/2562/0017",
            "startDate": "2019-08-26T17:00:00.000Z",
            "endDate": "2022-01-06T17:00:00.000Z",
            "loanAmount": "34560.00",
            "installmentAmount": "1231.00",
            "installmentLastAmount": "92.00",
            "installmentPeriodValue": 1,
            "installmentTimes": 29,
            "borrowerIdCardNo": "3959900370461",
            "guarantorIdCardNo": "3200101202795",
            "borrowerName": "นางพรรณี ชัยศรี",
            "guarantorName": "นางเรณู ประเสริฐวิทย์",
            "broughtForward": "1231.00",
            "totalPaidJanuary": "0.00",
            "totalPaidFebruary": "0.00",
            "totalPaidMarch": "0.00",
            "totalPaidApril": "0.00",
            "totalPaidMay": "0.00",
            "totalPaidJune": "0.00",
            "totalPaidJuly": "0.00",
            "totalPaidAugust": "0.00",
            "totalPaidSeptember": "0.00",
            "totalPaidOctober": "0.00",
            "totalPaidNovember": "0.00",
            "totalPaidDecember": "0.00",
            "totalPaidAllMonth": "0.00",
            "lastPaidDate": "2019-11-30T17:00:00.000Z",
            "currentDate": "2019-11-13",
            "installmentsTimesDue": "4",
            "currentTempExpectedPaidAmount": "4924.00",
            "installmentsAmountDue": "4924.000000000000000000000000000000",
            "tempPaidAmount": "6000.00",
            "paidAmount": "6000.00",
            "installmentsTimesOverDue": -1076,
            "installmentsAmountOverDue": 0
        },
        {
            "paymentType": "OFFICE",
            "outstandingDebtBalance": "34560.00",
            "documentDate": "2019-08-26T17:00:00.000Z",
            "documentNumber": "กท/2562/0017",
            "startDate": "2019-08-26T17:00:00.000Z",
            "endDate": "2022-01-06T17:00:00.000Z",
            "loanAmount": "34560.00",
            "installmentAmount": "1231.00",
            "installmentLastAmount": "92.00",
            "installmentPeriodValue": 1,
            "installmentTimes": 29,
            "borrowerIdCardNo": "1231231231231",
            "guarantorIdCardNo": "1231231231231",
            "borrowerName": "นางวันนี้ ที่รอคอย",
            "guarantorName": "นางคอย รอ",
            "broughtForward": "6000.00",
            "totalPaidJanuary": "0.00",
            "totalPaidFebruary": "0.00",
            "totalPaidMarch": "0.00",
            "totalPaidApril": "0.00",
            "totalPaidMay": "0.00",
            "totalPaidJune": "0.00",
            "totalPaidJuly": "0.00",
            "totalPaidAugust": "0.00",
            "totalPaidSeptember": "0.00",
            "totalPaidOctober": "0.00",
            "totalPaidNovember": "0.00",
            "totalPaidDecember": "0.00",
            "totalPaidAllMonth": "0.00",
            "lastPaidDate": "2019-11-30T17:00:00.000Z",
            "currentDate": "2019-11-13",
            "installmentsTimesDue": "4",
            "currentTempExpectedPaidAmount": "4924.00",
            "installmentsAmountDue": "4924.000000000000000000000000000000",
            "tempPaidAmount": "6000.00",
            "paidAmount": "6000.00",
            "installmentsTimesOverDue": -1076,
            "installmentsAmountOverDue": 0
        },
        {
            "paymentType": "CS",
            "outstandingDebtBalance": "34560.00",
            "documentDate": "2019-08-26T17:00:00.000Z",
            "documentNumber": "กท/2562/0017",
            "startDate": "2019-08-26T17:00:00.000Z",
            "endDate": "2022-01-06T17:00:00.000Z",
            "loanAmount": "34560.00",
            "installmentAmount": "1231.00",
            "installmentLastAmount": "92.00",
            "installmentPeriodValue": 1,
            "installmentTimes": 29,
            "borrowerIdCardNo": "1231231231231",
            "guarantorIdCardNo": "1231231231231",
            "borrowerName": "นางวันนี้ ที่รอคอย",
            "guarantorName": "นางคอย รอ",
            "broughtForward": "1231.00",
            "totalPaidJanuary": "0.00",
            "totalPaidFebruary": "0.00",
            "totalPaidMarch": "0.00",
            "totalPaidApril": "0.00",
            "totalPaidMay": "0.00",
            "totalPaidJune": "0.00",
            "totalPaidJuly": "0.00",
            "totalPaidAugust": "0.00",
            "totalPaidSeptember": "0.00",
            "totalPaidOctober": "0.00",
            "totalPaidNovember": "0.00",
            "totalPaidDecember": "0.00",
            "totalPaidAllMonth": "0.00",
            "lastPaidDate": "2019-11-30T17:00:00.000Z",
            "currentDate": "2019-11-13",
            "installmentsTimesDue": "4",
            "currentTempExpectedPaidAmount": "4924.00",
            "installmentsAmountDue": "4924.000000000000000000000000000000",
            "tempPaidAmount": "6000.00",
            "paidAmount": "6000.00",
            "installmentsTimesOverDue": -1076,
            "installmentsAmountOverDue": 0
        },
        {
            "paymentType": "OFFICE",
            "outstandingDebtBalance": "1320.00",
            "documentDate": "2019-09-16T17:00:00.000Z",
            "documentNumber": "กท/2562/0018",
            "startDate": "2019-09-16T17:00:00.000Z",
            "endDate": "2020-03-09T17:00:00.000Z",
            "loanAmount": "1320.00",
            "installmentAmount": "240.00",
            "installmentLastAmount": "120.00",
            "installmentPeriodValue": 1,
            "installmentTimes": 6,
            "borrowerIdCardNo": "3101502269132",
            "guarantorIdCardNo": "3101502269272",
            "borrowerName": "นางสาวลำดวน กิจวิทยี",
            "guarantorName": "นางสมจิตต์ บุญประโคน",
            "broughtForward": "12000.00",
            "totalPaidJanuary": "0.00",
            "totalPaidFebruary": "0.00",
            "totalPaidMarch": "0.00",
            "totalPaidApril": "0.00",
            "totalPaidMay": "0.00",
            "totalPaidJune": "0.00",
            "totalPaidJuly": "0.00",
            "totalPaidAugust": "0.00",
            "totalPaidSeptember": "0.00",
            "totalPaidOctober": "0.00",
            "totalPaidNovember": "0.00",
            "totalPaidDecember": "0.00",
            "totalPaidAllMonth": "0.00",
            "lastPaidDate": "2008-12-03T17:00:00.000Z",
            "currentDate": "2019-11-13",
            "installmentsTimesDue": "3",
            "currentTempExpectedPaidAmount": "720.00",
            "installmentsAmountDue": "720.000000000000000000000000000000",
            "tempPaidAmount": "12000.00",
            "paidAmount": "12000.00",
            "installmentsTimesOverDue": -11280,
            "installmentsAmountOverDue": 0
        },
        {
            "paymentType": "OFFICE",
            "outstandingDebtBalance": "1320.00",
            "documentDate": "2019-09-16T17:00:00.000Z",
            "documentNumber": "กท/2562/0018",
            "startDate": "2019-09-16T17:00:00.000Z",
            "endDate": "2020-03-09T17:00:00.000Z",
            "loanAmount": "1320.00",
            "installmentAmount": "240.00",
            "installmentLastAmount": "120.00",
            "installmentPeriodValue": 1,
            "installmentTimes": 6,
            "borrowerIdCardNo": "1809900616724",
            "guarantorIdCardNo": "1809900616724",
            "borrowerName": "นายสิทธิชัย สันติวรกุล",
            "guarantorName": "นายสิทธิชัย สันติวรกุล",
            "broughtForward": "12000.00",
            "totalPaidJanuary": "0.00",
            "totalPaidFebruary": "0.00",
            "totalPaidMarch": "0.00",
            "totalPaidApril": "0.00",
            "totalPaidMay": "0.00",
            "totalPaidJune": "0.00",
            "totalPaidJuly": "0.00",
            "totalPaidAugust": "0.00",
            "totalPaidSeptember": "0.00",
            "totalPaidOctober": "0.00",
            "totalPaidNovember": "0.00",
            "totalPaidDecember": "0.00",
            "totalPaidAllMonth": "0.00",
            "lastPaidDate": "2008-12-03T17:00:00.000Z",
            "currentDate": "2019-11-13",
            "installmentsTimesDue": "3",
            "currentTempExpectedPaidAmount": "720.00",
            "installmentsAmountDue": "720.000000000000000000000000000000",
            "tempPaidAmount": "12000.00",
            "paidAmount": "12000.00",
            "installmentsTimesOverDue": -11280,
            "installmentsAmountOverDue": 0
        }
    ]
}